README.md
setup.py
navegador5/__init__.py
navegador5/body.py
navegador5/file_toolset.py
navegador5/head.py
navegador5/html_tool.py
navegador5/jq.py
navegador5/js_random.py
navegador5/jsurl.py
navegador5/shell_cmd.py
navegador5/solicitud.py
navegador5/status_code.py
navegador5/time_utils.py
navegador5/url_tool.py
navegador5/xquery.py
navegador5.egg-info/PKG-INFO
navegador5.egg-info/SOURCES.txt
navegador5.egg-info/dependency_links.txt
navegador5.egg-info/top_level.txt
navegador5/content_parser/__init__.py
navegador5/content_parser/amf0_decode.py
navegador5/content_parser/amf3_decode.py
navegador5/cookie/__init__.py
navegador5/cookie/cookie.py
navegador5/cookie/rfc6265.py